CHANGELOG.txt
LICENCE.txt
MANIFEST.in
README.txt
setup.py
RecTulips/__init__.py
RecTulips.egg-info/PKG-INFO
RecTulips.egg-info/SOURCES.txt
RecTulips.egg-info/dependency_links.txt
RecTulips.egg-info/requires.txt
RecTulips.egg-info/top_level.txt